langur/__init__.py
langur/actions.py
langur/agent.py
langur/behavior.py
langur/connector.py
langur/langur.py
langur/llm.py
langur/signals.py
langur/viewer.py
langur/baml_client/__init__.py
langur/baml_client/async_client.py
langur/baml_client/globals.py
langur/baml_client/inlinedbaml.py
langur/baml_client/partial_types.py
langur/baml_client/sync_client.py
langur/baml_client/tracing.py
langur/baml_client/type_builder.py
langur/baml_client/types.py
langur/baml_src/assumptions.baml
langur/baml_src/clients.baml
langur/baml_src/fill_params.baml
langur/baml_src/generators.baml
langur/baml_src/planner.baml
langur/baml_src/think.baml
langur/connectors/__init__.py
langur/connectors/llm.py
langur/connectors/terminal.py
langur/connectors/web.py
langur/connectors/workspace.py
langur/graph/__init__.py
langur/graph/edge.py
langur/graph/graph.py
langur/graph/node.py
langur/util/baml_type_converter.py
langur/util/model_builder.py
langur/util/registries.py
langur/util/schema.py
langur/util/test_schema.py
langur/util/type_index.py
langur/workers/assumer.py
langur/workers/executor.py
langur/workers/planner.py
langur/workers/task.py
langur/workers/worker.py
langur-0.1.1.dist-info/METADATA
langur-0.1.1.dist-info/WHEEL
langur-0.1.1.dist-info/licenses/LICENSE
langur-0.1.1.dist-info/RECORD
