Metadata-Version: 2.3
Name: langur
Version: 0.1.1
Summary: Langur makes it simple to build consistent, observable, and portable LLM agents
Project-URL: Homepage, https://github.com/anerli/langur
Project-URL: Discord, https://discord.gg/wSBSP56V7U
Author-email: Anders Lie <anders@langur.ai>
License-File: LICENSE
Requires-Python: >=3.11
Requires-Dist: baml-py>=0.66.0
Requires-Dist: cuid2>=2.0.1
Requires-Dist: fs>=2.4.16
Requires-Dist: ipykernel>=6.29.5
Requires-Dist: ipysigma>=0.24.3
Requires-Dist: nest-asyncio>=1.6.0
Requires-Dist: networkx>=3.4.2
Requires-Dist: pydantic>=2.9.2
Provides-Extra: langchain
Requires-Dist: langchain-community>=0.3.5; extra == 'langchain'
Requires-Dist: langchain-core>=0.3.15; extra == 'langchain'
